{"response":[{"_id":"51a9fd0328217f89770001fc","accessibility_options":["Not wheelchair accessible at this time"],"agency":null,"ask_for":null,"city":"San Mateo","coordinates":[-122.319502,37.572696],"description":"Acts as a liaison between Tongans in the U.S. and various agencies, translates and interprets and provides services to Tongans in the community Acts as a liaison between Tongans and various local, national and international bureaucracies. Services include the preparation of documents, assistance with immigration, advocacy and language interpretation in the courts, schools, etc., and counseling to prevent alcohol and drug use and child abuse. Also provides information about Tongan culture and customs and letters of introduction to anyone interested in travelling to Tonga. Issues travel documents to Tongans for travel to any foreign country. There is a branch office in the Los Angeles area.","eligibility_requirements":"None","emails":null,"faxes":null,"fees":"Varies according to service. Cash, checks and money orders accepted","funding_sources":null,"how_to_apply":"Apply by phone or mail","keywords":["COMMUNITY SERVICES","Group Support","Immigration/Naturalization","Information and Referral","Interpretation/Translation","LEGAL AND CRIMINAL JUSTICE SERVICES","Certificates/Forms Assistanc","Tongan Community","Cultural/Racial Issues"],"languages_spoken":["Tongan"],"latitude":null,"leaders":null,"longitude":null,"market_match":null,"name":"National Office for Tongan/Pacific American Affairs.","payments_accepted":null,"phones":[[{"number":"650 342-1292","phone_hours":"(Monday-Friday, 9-5)"}]],"products_sold":null,"service_areas":null,"service_hours":"Monday-Friday, 9-5; Saturday by appointment","service_wait":"No wait","services_provided":null,"state":"CA","street_address":"18 North Humboldt Street","target_group":"Tongan people, Pacific Americans or anyone interested in Tonga and the Pacific countries","transportation_availability":"SAMTRANS, CALTRAIN stop within 2 blocks","ttys":null,"urls":null,"zipcode":"94401"},{"_id":"51a9fd0228217f8977000146","accessibility_options":["Restroom","Special parking","Wheelchair accessible"],"agency":"San Mateo City Parks and Recreation Department.","ask_for":null,"city":"San Mateo","coordinates":[-122.324568,37.573239],"description":"A recreation and community service center for the north central San Mateo area, operated by the City of San Mateo. Offers activities and classes for persons of all ages, from preschool up. Sports, games, dance, fitness and arts and crafts classes are offered. Holds special events each holiday season and summer day camps for children. Has an indoor gym, swimming pool and multipurpose activity rooms.   As a Senior Nutrition Program Site, provides a hot, nutritious chef-prepared lunch, Tuesday and Thursday, 12 noon to 1 pm  for persons age 60 or over and spouse of any age. Space is limited; call 522-7498 to make reservations. $3 suggested donation.","eligibility_requirements":"None","emails":null,"faxes":null,"fees":"Vary according to activity. Many activities free. Cash, checks and credit cards accepted","funding_sources":null,"how_to_apply":"Walk in or call for information","keywords":["ADULT PROTECTION AND CARE SERVICES","Meal Sites/Home-delivered Meal","RECREATION/LEISURE SERVICES","Arts and Crafts","Parks/Playground","Special Events/Entertainment","Sports/Games/Exercise","Low Cost Meals","Facilities/Community Centers","Senior Centers","Older Adults"],"languages_spoken":["Spanish"],"latitude":null,"leaders":null,"longitude":null,"market_match":null,"name":"Martin Luther King Center.","payments_accepted":null,"phones":[[{"number":"650 522-7470","phone_hours":"(Monday-Thursday, 9-9; Friday, 9-6)"}]],"products_sold":null,"service_areas":null,"service_hours":"Monday-Thursday, 9-9; Friday, 9-6","service_wait":"No wait","services_provided":"A community service center offering recreational activities and classes to residents of the city of San Mateo.","state":"CA","street_address":"725 Monte Diablo Avenue","target_group":"Teens and young adults, preschoolers, senior citizens","transportation_availability":"SAMTRANS stops within 1 block","ttys":null,"urls":["http://www.cityofsanmateo.org"],"zipcode":"94401"},{"_id":"51a9fd0328217f897700016b","accessibility_options":["Wheelchair accessible"],"agency":"St. Vincent de Paul Society.","ask_for":null,"city":"San Mateo","coordinates":[-122.325092,37.568303],"description":"Assists families and individuals with emergencies such as shelter, food, clothing, furniture, transportation and medicine through 34 small working groups called conferences. St. Vincent de Paul members visit the home to assess needs and offer service. Also supports those in recovery programs.     Three Homeless Help Centers (described separately) provide weekday lunches, continental breakfasts, clothing vouchers, laundry, toiletries, identification and transportation assistance to individuals without a permanent address. The North County Homeless Help Center and Cafe St. Vincent are located at 344 Grand Avenue, South San Francisco (650-589-9039), open Monday through Saturday, 10 am-12 noon. The Redwood City Homeless Help Center is housed in the Fair Oaks Community Center, 2600 Middlefield Road (650-780-7500), and is open 1-2 pm weekdays. The San Mateo site is at 50 North B Street and is open 10 am-12 noon Monday through Friday (650-343-9251). A meal is also served on Monday at 5 pm, at St. Francis Church, 420 Bay Road, East Palo Alto. Peninsula Family Resource Center (PFRC) arranges home visits for persons in need of rental and utilities assistance (homelessness prevention), food, clothes, furniture and other material needs. Call 650-343-4403 Monday-Friday, 10-12 and 1-4, to make arrangements. Also coordinates summer camp scholarships for youth and holiday assistance programs. Restorative Justice Ministry is a full-time jail ministry program that provides spiritual guidance, religious services, tutoring, support and assistance to those incarcerated in the San Mateo County jail facilities and to their families. Jail/prison after care program provides post-release support. Contact the SVdP Jail Chaplain at 650-366-9847. Catherine's Center is a supportive residential program for ten women at a time who were previously incarcerated. Five thrift stores are located in San Mateo County: Daly City at 6256 Mission Street (650-992-9271); Redwood City at 2406 El Camino Real (650-366-6367); San Bruno at 1600 El Camino Real (650-588-5767); San Mateo at 40 North B Street (650-347-5101); South San Francisco at 344 Grand Avenue (650-589-8445). Donations can be made at store locations or call 650 871-6844 for donation or computer re-cycling pick-up.  For vehicle donations call 800-937-7837.","eligibility_requirements":"None","emails":["svdpinfo@yahoo.com"],"faxes":["650 343-9495"],"fees":"None","funding_sources":null,"how_to_apply":"Apply by phone or visit a Homeless Help Center located in Redwood City, San Mateo and South San Francisco","keywords":["ADULT PROTECTION AND CARE SERVICES","Meal Sites/Home-delivered Meal","COMMODITY SERVICES","Clothing/Personal Items","Furniture/Appliances","EMERGENCY SERVICES","Food Boxes/Food Vouchers","FINANCIAL ASSISTANCE SERVICES","Health","Housing","Utilities","RECREATION/LEISURE SERVICES","Camperships","Soup Kitchens","Homeless Motel Vouchers","Housing Expense Assistance","Clothing","Laundry Facilities","Thrift Shops","Utility Assistance","Identification Cards","Prison Ministries","Emergency Medical Care","Low Income","Homeless People","Religious Groups/Communities"],"languages_spoken":["Spanish"],"latitude":null,"leaders":null,"longitude":null,"market_match":null,"name":"San Mateo County District Council.","payments_accepted":null,"phones":[[{"number":"650 343-4405","department":"Directory","phone_hours":"(24 hours daily)"}],[{"number":"650 343-4403","department":"Emergency Helpline","phone_hours":"(Monday-Friday, 9-12, 1-4)"}]],"products_sold":null,"service_areas":null,"service_hours":"Emergency Helpline: Monday - Friday, 9-4","service_wait":"No wait","services_provided":"Coordinates the Society's county-wide emergency services and provides homeless services to persons in the central county area.","state":"CA","street_address":"50 North B Street","target_group":"Families or individuals seeking emergency help for food, clothing, rental and utility assistance. Homeless individuals in need of food, basic services and vouchers for San Mateo County shelters","transportation_availability":"SAMTRANS, CALTRAIN stop within 1 block","ttys":null,"urls":["http://www.svdp-sanmateoco.org"],"zipcode":"94401"},{"_id":"51a9fd0928217f8977000633","accessibility_options":["Wheelchair accessible"],"agency":"St. Vincent de Paul Society.","ask_for":null,"city":"San Mateo","coordinates":[-122.325092,37.568303],"description":"Offers homeless or low-income persons clean clothing, toiletries, mail, telephone, laundry  service, DMV identification and transportation help (bus fare, gasoline, etc.) Assists with work-related needs such as uniforms, work boots, union dues and job referrals. Provides emergency medical assistance, substance abuse center fees, and referrals to mental health  and other resources. Distributes vouchers to county shelters or sleeping bags when shelters are full. A free bag lunch and continental breakfast are served to homeless persons on weekdays, 10 am to 12  noon.  ","eligibility_requirements":"None","emails":["svdpinfo@yahoo.com"],"faxes":null,"fees":"None","funding_sources":null,"how_to_apply":"Walk in","keywords":["COMMODITY SERVICES","Clothing/Personal Items","EMERGENCY SERVICES","Food Boxes/Food Vouchers","Soup Kitchens","Homeless Motel Vouchers","Clothing","Laundry Facilities","Identification Cards","Emergency Medical Care","Low Income","Homeless People"],"languages_spoken":["Spanish"],"latitude":null,"leaders":null,"longitude":null,"market_match":null,"name":"San Mateo County District Council., San Mateo Homeless Help Center.","payments_accepted":null,"phones":[[{"number":"650 343-9251"}]],"products_sold":null,"service_areas":null,"service_hours":"Monday-Friday, 9:45 am - 11:45 am","service_wait":"No wait","services_provided":"Food, clothing and other services for homeless persons.","state":"CA","street_address":"50 North B Street","target_group":"Homeless persons or persons without cooking facilities","transportation_availability":"SamTrans, CALTRAIN stop within 1 block","ttys":null,"urls":["http://www.svdp-sanmateoco.org"],"zipcode":"94401"},{"_id":"51a9fd0828217f8977000554","accessibility_options":null,"agency":null,"ask_for":null,"city":"San Mateo","coordinates":[-122.319733,37.565738],"description":"A social, educational and cultural group for women of Japanese ancestry. The group is English-speaking. Meets the second, fourth and fifth Wednesdays of the month at the Japanese Community Center, 415 South Claremont, San Mateo.","eligibility_requirements":"None","emails":null,"faxes":null,"fees":"Membership: $10 per year. Cash accepted","funding_sources":null,"how_to_apply":null,"keywords":["Special Interest Clubs","Older Adults","Cultural/Racial Issues"],"languages_spoken":["Japanese"],"latitude":null,"leaders":null,"longitude":null,"market_match":null,"name":"Tomodachi.","payments_accepted":null,"phones":[[{"number":"650 343-2793","phone_hours":"(Monday-Friday, 10-4)"}]],"products_sold":null,"service_areas":null,"service_hours":null,"service_wait":null,"services_provided":"A social, educational and cultural group for women, age 65 or over, of Japanese ancestry.","state":"CA","street_address":"415 South Claremont Street","target_group":"Senior women","transportation_availability":null,"ttys":null,"urls":null,"zipcode":"94401"},{"_id":"51a9fd0128217f8977000094","accessibility_options":["Not wheelchair accessible at this time"],"agency":null,"ask_for":null,"city":"San Mateo","coordinates":[-122.319733,37.565738],"description":"Serves as an information and referral and drop-in center for the Japanese-speaking community and other Asians. Has a lending library of Japanese videos and books, as well as English language books and videos about Asians. Assists students of Japanese-American studies with projects and research. Provides oral interpretation and translation of written documents to the community at large. There is no fee for this service but an appointment is required. A center advisory committee meets on the second Wednesday of each month at 7 pm at the center. The center also sponsors various educational and cultural meetings throughout the year. Sponsors the Peninsula Widowed Group for any widowed person which meets the third Sunday of every month from 2-4 pm. Sponsors two groups for seniors: Kiraku Kai, a senior men's group, and Tomodachi, an English-speaking club for senior women. Tiny Tots music group meets Wednesdays and play group Fridays. Japanese flower arranging (Ikebana), embroidery (Bunka shishu), and Bonsai classes are held. Martial arts classes include Shorinj, Kempo, and Ki Aikido. A monthly group studies Kabuki, a form of classical Japanese theater. Also provides blood pressure screening the first Wednesday of every month, 1-2 pm, and flu shots annually. Formerly known as Japanese American Citizens League Community Center (JACL).","eligibility_requirements":"None","emails":null,"faxes":["650 343-2881"],"fees":"None for service. Dues vary from $50-$95","funding_sources":null,"how_to_apply":"Call for an appointment or walk in","keywords":["COMMUNITY SERVICES","Group Support","Immigration/Naturalization","Information and Referral","Interpretation/Translation","RECREATION/LEISURE SERVICES","Special Events/Entertainment","Community Facilities/Centers","Cultural/Racial Issues"],"languages_spoken":["Japanese"],"latitude":null,"leaders":null,"longitude":null,"market_match":null,"name":"San Mateo Japanese American Community Center.","payments_accepted":null,"phones":[[{"number":"650 343-2793","phone_hours":"(Monday-Friday, 10-4)"}]],"products_sold":null,"service_areas":null,"service_hours":"Monday-Friday, 10-4","service_wait":"No wait","services_provided":"Serves as an information and referral and drop-in center for the Japanese-speaking community and other Asians.","state":"CA","street_address":"415 South Claremont Street","target_group":"Japanese-Americans and recent arrivals from Japan (non-English or limited English-speaking Japanese)","transportation_availability":"SAMTRANS stops within 3 blocks","ttys":null,"urls":["http://www.smjacc.org"],"zipcode":"94401"},{"_id":"51a9fd0128217f897700003b","accessibility_options":["Wheelchair accessible"],"agency":null,"ask_for":null,"city":"San Mateo","coordinates":[-122.319155,37.565443],"description":"Provides legal advice and counsel on civil matters to low income individuals, families and groups. Civil cases include divorce, domestic violence, landlord/tenant issues, government benefits, public housing problems, elder abuse and consumer complaints (seniors). The Clients' Rights Advocate and the Kids in Crisis (KIC) Project help persons with disabilities with problems related to the Americans with Disabilities Act, transit and para-transit, the Golden Gate Regional Center, the San Mateo County Mental Health Division, Social Security Administration, the Regional Center and California Children Services. The Health Consumer Center assists people with problems or questions relating to Medi-Cal, Healthy Families, Healthy Kids, Medicare, Well, and some private insurance. The Teen Parent Project staff works with teen parents on such problems as paternity, domestic violence, benefits and support. The Home Savers provides advice and representation to individuals at risk of eviction. The Family Advocacy Program (FAP), a collaboration with Lucille Packard Children's Hospital, helps pediatric patients with issues affecting their health. The Seniors Advocates Program provides legal assistance for the elderly concerning elder abuse and consumer issues. Advance Health Directive Clinics are also held several times a year. Staff can visit homebound people.","eligibility_requirements":"Low income, disabled, or senior","emails":["mshawver@legalaidsmc.org"],"faxes":["650 558-0673"],"fees":"None for attorney services. Donations welcome","funding_sources":null,"how_to_apply":"Apply by phone for appointment and some clinics","keywords":["Certificates/Forms Assistance","Legal Counseling","Legal Representation","Landlord/Tenant Assistance"],"languages_spoken":["French","Russian","Spanish"],"latitude":null,"leaders":null,"longitude":null,"market_match":null,"name":"Legal Aid Society of San Mateo County.","payments_accepted":null,"phones":[[{"number":"800 381-8898"}],[{"number":"650 558-0915","phone_hours":"(Monday-Friday, 9-12, 1-5)"}]],"products_sold":null,"service_areas":null,"service_hours":"Monday-Friday, 9-12, 1-5","service_wait":"1 to 2 weeks. Emergencies seen immediately","services_provided":"Legal advice and counsel on civil matters for individuals, families and groups whose incomes are below an established level.","state":"CA","street_address":"521 East 5th Avenue","target_group":"Low-income residents of San Mateo County, persons with disabilities, seniors, teen parents","transportation_availability":"SAMTRANS stops within 4 blocks","ttys":["650 558-0786"],"urls":["http://www.legalaidsmc.org"],"zipcode":"94402"},{"_id":"51a9fd0328217f89770001ef","accessibility_options":["Wheelchair accessible"],"agency":"Legal Aid Society of San Mateo County.","ask_for":null,"city":"San Mateo","coordinates":[-122.319155,37.565443],"description":"Provides free attorney service to persons age 60 or over, with priority given to disadvantaged and low-income persons. Assists with legal problems in such areas as government benefits (social security, supplemental security income (SSI), Medi-Cal, In-Home Supportive Sevices (IHSS), Cash Assistance Program for Immigrants (CAPI), general assistance (GA), and the food stamp program), health, housing (including landlord/tenant issues) and consumer protection and debt collection. Provides legal assistance to remedy or prevent elder abuse, including emotional, physical and financial abuse. Will send an attorney or legal assistant to homebound persons. Efforts will be made to see a person immediately in an emergency.","eligibility_requirements":"Age 60 or over","emails":["mshawver@legalaidsmc.org"],"faxes":["650 558-0673"],"fees":"None for attorney services. Donations welcome","funding_sources":null,"how_to_apply":"Apply by phone for appointment","keywords":["ADULT PROTECTION AND CARE SERVICES","Guardianship/Conservatorship","LEGAL AND CRIMINAL JUSTICE SERVICES","Certificates/Forms Assistance","Defense Representation","Older Adults"],"languages_spoken":["Chinese (Cantonese)","Russian","Spanish"],"latitude":null,"leaders":null,"longitude":null,"market_match":null,"name":"Senior Advocates Program.","payments_accepted":null,"phones":[[{"number":"800 381-8898"}],[{"number":"650 558-0915","phone_hours":"(Monday-Friday, 9-12, 1-5)"}]],"products_sold":null,"service_areas":null,"service_hours":"Monday - Friday, 9-12, 1-5","service_wait":"1-2 weeks. No wait in an emergency","services_provided":"Free attorney service for persons age 60 or over, with priority given to minority and low-income persons.","state":"CA","street_address":"521 East 5th Avenue","target_group":"Senior citizens","transportation_availability":"SAMTRANS stops within 2 blocks","ttys":["650 558-0786"],"urls":["http://www.legalaidsmc.org"],"zipcode":"94402"},{"_id":"51a9fd0128217f8977000078","accessibility_options":["Wheelchair accessible"],"agency":null,"ask_for":null,"city":"San Mateo","coordinates":[-122.321278,37.565458],"description":"Homesharing program that matches persons with a home or apartment to share with those seeking housing, thereby reducing housing costs for both. The Self-Sufficiency Program provides housing, case management and supportive services to heads of households motivated to achieve self-reliance.  The agency also owns and manages properties intended to provide affordable housing for individuals and families. ","eligibility_requirements":"Resident of San Mateo County or desiring to become a resident","emails":["mailbox@hiphousing.org"],"faxes":["650 348-0284"],"fees":"None. ","funding_sources":null,"how_to_apply":"Apply by phone for appointment","keywords":["ADMINISTRATION AND PLANNING SERVICES","Administration and Planning","FINANCIAL ASSISTANCE SERVICES","Housing","HOUSING SERVICES","Family Housing/Shared Housing","Relocation","Roommate/Housemate Matching Assistance","Low Income/Subsidized Rental Housing"],"languages_spoken":["Chinese (Cantonese)","German","Spanish","Tagalog"],"latitude":null,"leaders":null,"longitude":null,"market_match":null,"name":"Human Investment Project (HIP Housing).","payments_accepted":null,"phones":[[{"number":"650 348-6660","phone_hours":"(Monday-Friday, 8-5)"}],[{"number":"650 301-8414","department":"Daly City"}],[{"number":"650 780-7511","department":"Redwood City"}],[{"number":"650 829-3971","department":"South San Francisco"}]],"products_sold":null,"service_areas":null,"service_hours":"Monday-Friday, 8-5","service_wait":"No wait","services_provided":"Sponsors a number of programs designed to help senior citizens, single parents or persons with low or modest incomes to obtain housing or remain in their own homes.","state":"CA","street_address":"364 South Railroad Avenue","target_group":"Anyone in need of housing or a housemate, single parents and low-income families motivated to transition from welfare to work","transportation_availability":"SAMTRANS stops within 2 blocks, CALTRAIN stops within 1 block","ttys":null,"urls":["http://www.hiphousing.org"],"zipcode":"94401"},{"_id":"51a9fd0128217f8977000037","accessibility_options":null,"agency":null,"ask_for":null,"city":"San Mateo","coordinates":[-122.324,37.5663],"description":null,"eligibility_requirements":null,"emails":null,"faxes":null,"fees":null,"funding_sources":null,"how_to_apply":null,"keywords":["farmers' market","food","produce"],"languages_spoken":null,"latitude":37.5663,"leaders":null,"longitude":-122.324,"market_match":false,"name":"Urban Table Certified Farmer's Market","payments_accepted":[],"phones":null,"products_sold":["Prepared Food"],"schedule":"April 1 - October 28 Monday 5:00 PM to 8:30 PM","service_areas":null,"service_hours":null,"service_wait":null,"services_provided":null,"state":"California","street_address":"385 1st Avenue","target_group":null,"transportation_availability":null,"ttys":null,"urls":["https://www.facebook.com/UrbanMarketSanMateo"],"zipcode":null},{"_id":"51a9fd0328217f89770001e8","accessibility_options":null,"agency":"Mills-Peninsula Health Services.","ask_for":null,"city":"San Mateo","coordinates":[-122.325834,37.565958],"description":"A personal emergency response system that connects persons to the Emergency Response Center at Mills-Peninsula Health Services for any emergency situation. The individual presses the waterproof help button, worn on a chain around the neck, which automatically dials the hospital. If they are unable to reach the subscriber by phone, the hospital calls someone from the list of \"responders\" on file to check on the individual. Various units are available including a voice-activated model.    Staff will make presentations on the Lifeline service for groups and clubs as requested.","eligibility_requirements":"Resident of area served who is ill, elderly, disabled or living alone","emails":["castroj5@sutterhealth.org"],"faxes":["650 696-4711"],"fees":"$30 per month for the Dual Unit (telephone and Lifeline unit combined), $35 per month for VoiceAssist unit, $50 installation charge. $40 for the phone unit, $35 for the standard unit, $50 installation charge. Cash, checks and money orders accepted","funding_sources":null,"how_to_apply":"Walk in or apply by phone or mail","keywords":["COMMUNITY SERVICES","Speakers","EMERGENCY SERVICES","Medical Assistance","Older Adults"],"languages_spoken":["AT&T Language Line"],"latitude":null,"leaders":null,"longitude":null,"market_match":null,"name":"Lifeline.","payments_accepted":null,"phones":[[{"number":"650 696-4823","phone_hours":"(Monday-Friday, 9-2)"}]],"products_sold":null,"service_areas":null,"service_hours":"Monday-Friday, 9-2","service_wait":"No wait","services_provided":"Provides an electronic communication system which links the ill, elderly or disabled person, or anyone adjusting to living alone, to the hospital emergency room.","state":"CA","street_address":"100 South San Mateo Drive","target_group":"Disabled persons, people living alone","transportation_availability":"Not necessary for service","ttys":null,"urls":["http://www.mills-peninsula.org"],"zipcode":"94401"},{"_id":"51a9fd0828217f89770005ab","accessibility_options":["Elevator","Ramp","Restroom","Special parking","Wheelchair accessible"],"agency":"Mills-Peninsula Health Services.","ask_for":null,"city":"San Mateo","coordinates":[-122.325834,37.565958],"description":"Provides outpatient health services including surgery, cancer care, diagnostic cardiology and renal dialysis. Also offers inpatient rehabilitation, breast health services and non-acute emergency services. The Recovery Care Inn offers post-surgical care for up to three days for otherwise healthy outpatient surgery patients. The Mack E. Mickelson Center provides arthritis services, cardiac rehabilitation, occupational and physical therapy, speech therapy, pediatric rehabiliation and a fitness center. A pool for aquatic therapy and exercise is available to all programs. Complementary medicine programs behavioral health and chemical dependency programs, biofeedback, nutrition counseling and pain management.","eligibility_requirements":"None","emails":null,"faxes":null,"fees":"Vary according to service. Medi-Cal, Medicare, private insurance accepted","funding_sources":null,"how_to_apply":"Apply by phone or come in person","keywords":["HEALTH SERVICES","Inpatient Care","Outpatient Care","Hospitals"],"languages_spoken":null,"latitude":null,"leaders":null,"longitude":null,"market_match":null,"name":"Mills Health Center.","payments_accepted":null,"phones":[[{"number":"650 696-5400"}]],"products_sold":null,"service_areas":null,"service_hours":"Vary according to service","service_wait":"No wait","services_provided":"Comprehensive acute, outpatient and emergency care services.","state":"CA","street_address":"100 South San Mateo Drive","target_group":null,"transportation_availability":"SAMTRANS stops at the door","ttys":null,"urls":["http://www.mills-peninsula.org"],"zipcode":"94401"},{"_id":"51a9fd0428217f8977000229","accessibility_options":["Restroom","Special parking","Wheelchair accessible"],"agency":"Mills-Peninsula Health Services.","ask_for":null,"city":"San Mateo","coordinates":[-122.325834,37.565958],"description":"A volunteer organization that works in many areas of the hospital, including the installation and maintenance of Lifeline units. A scholarship fund of approximately $40,000 a year is raised from the gift shop earnings, gratuities and private donations. Scholarships of varying amounts are awarded to young people who are pursuing a career in the hospital related, health care fields such as an RN, LVN, pharmacist, physical therapist or occupational therapist. No scholarships are available for dental or medical school students.","eligibility_requirements":"Age 14 or over. Junior volunteers must also be freshmen in high school","emails":null,"faxes":null,"fees":null,"funding_sources":null,"how_to_apply":"Walk in. Documentation of clear PPD or chest x-ray (age 35 or over) required","keywords":["COMMUNITY SERVICES","Volunteer Assistance","FINANCIAL ASSISTANCE SERVICES","Education/Child Care/Recreation","Youth"],"languages_spoken":["Interpreter"],"latitude":null,"leaders":null,"longitude":null,"market_match":null,"name":"Mills-Peninsula Auxillary.","payments_accepted":null,"phones":[[{"number":"650 696-4175","phone_hours":"(Monday-Friday, 8:30-4)"}]],"products_sold":null,"service_areas":null,"service_hours":"Monday-Friday, 8:30-4:30","service_wait":"No wait","services_provided":"Provides volunteers to work in many areas of the hospital, awards scholarships to young people pursuing a health-related career.","state":"CA","street_address":"100 South San Mateo Drive","target_group":"Junior volunteers - age 14-18. Adult volunteers - age 18 or over","transportation_availability":"SAMTRANS stops within 1 block","ttys":null,"urls":null,"zipcode":"94401"},{"_id":"51a9fd0228217f8977000161","accessibility_options":["Ramp","Restroom","Special parking","Wheelchair accessible"],"agency":"Mills-Peninsula Health Services.","ask_for":null,"city":"San Mateo","coordinates":[-122.325834,37.565958],"description":"An intensive out-patient behavioral health treatment program designed primarily for seniors who have difficulty coping with such problems as loss of health or spouse, loss of job, isolation, reduced income and status. Each person's economic, physical, social and emotional circumstances are considered in planning appropriate activities. Staff also work with the families to resolve problems that may exist at home. Clients are encouraged to help plan activities and to participate actively. Other services include group therapy, art, music and exercise therapy. A hot meal is provided. The Senior Dual Diagnosis Treatment program is held three days a week, 10 am-2 pm, for individuals age 55 or over with dual diagnosis issues (for example, chemical dependency and depression or bi-polar disorder). The program includes individual, group and family counseling, exercise and physical therapy, assertiveness training, stress reduction and an introduction to Alcoholics Anonymous. Educational presentations are offered on all aspects of substance abuse and codependency. Aftercare is provided. Formerly known as Midpeninsula Health Services, Senior Mental Health Program.","eligibility_requirements":"Age 55 or over","emails":["eigenbs@sutterhealth.org"],"faxes":["650 696-4430"],"fees":"Vary according to service. Cash, credit cards, Medicare, military insurance and private insurance accepted","funding_sources":null,"how_to_apply":"Apply by phone at Intake Department (650-696-4666)","keywords":["ADULT PROTECTION AND CARE SERVICES","Adult Day Care","ALCOHOLISM SERVICES","Day Treatment","Family Support","DRUG ABUSE SERVICES","MENTAL HEALTH SERVICES","Group Counseling","Individual Counseling","Outpatient Mental Health Facilities","Older Adults"],"languages_spoken":null,"latitude":null,"leaders":null,"longitude":null,"market_match":null,"name":"Senior Outpatient Behavioral Health Program.","payments_accepted":null,"phones":[[{"number":"650 696-4256","phone_hours":"(Monday, Tuesday, Thursday, Friday, 8:30-3)"}]],"products_sold":null,"service_areas":null,"service_hours":"Monday, Tuesday, Thursday, Friday, 10-2","service_wait":"1-3 days","services_provided":"A day treatment program for persons age 50 or over who are dealing with depression, symptoms of loss, problems of social isolation or substance abuse.","state":"CA","street_address":"100 South San Mateo Drive","target_group":"Seniors with symptoms of depression, loss, social isolation, anxiety, displaying marked changes in eating and sleeping habits, alcohol and/or drug problems and seniors with a dual diagnosis","transportation_availability":"SAMTRANS stops within 2 blocks. Center provides transportation through Redi-Wheels within San Mateo County for those unable to utilize other means","ttys":null,"urls":["http://www.mills-peninsula.org"],"zipcode":"94401"},{"_id":"51a9fd0228217f897700015a","accessibility_options":["Ramp","Special parking","Wheelchair accessible"],"agency":"California State Department of Motor Vehicles (DMV).","ask_for":null,"city":"San Mateo","coordinates":[-122.323599,37.579174],"description":"Accepts applications and administers written tests for all licenses. Registers vehicles (cars, trucks, construction vehicles and other vehicles that use public streets), administers driving tests for all but commercial vehicles, handles driver's license renewals, identification cards, occupational licensing (salespersons), registration of on- and off-the-road vehicles, including boats and transfers of registration for both original and used vehicles and boats. On-the-road driver's test by appointment only.   Disabled persons who are severely mobility impaired may apply at this office for a placard to display on the car in which they are riding, enabling them to park in designated handicapped parking spaces.","eligibility_requirements":"Driver's permit: age 15 1/2 with completion of driver's education and enrollment in driver's training. Driver's license: age 16 with driver's education and driver training completed plus 6 months of possessing a learner's permit","emails":null,"faxes":null,"fees":"Registration and license fees vary. Cash, checks, debit cards and money orders accepted","funding_sources":null,"how_to_apply":"An appointment is recommended for conducting any business transactions at the DMV. An appointment is required for behind-the-wheel drive tests","keywords":["LEGAL AND CRIMINAL JUSTICE SERVICES","Certificates/Forms Assistance","Driver Licenses","Motor Vehicle Registration"],"languages_spoken":["Chinese (Mandarin)","Filipino (Tagalog)","Hindi","Panjabi","Spanish"],"latitude":null,"leaders":null,"longitude":null,"market_match":null,"name":"San Mateo Office.","payments_accepted":null,"phones":[[{"number":"800 777-0133","phone_hours":"(Monday, Tuesday, Thursday, Friday, 8-5; Wednesday, 9-5)"}]],"products_sold":null,"service_areas":null,"service_hours":"Monday, Tuesday, Thursday, Friday, 8-5; Wednesday, 9-5","service_wait":"Under 30 minutes; minimal wait with an appointment","services_provided":"Administers written and road tests for driver's licenses for all types of vehicles, issues identification cards, occupational licensing and registration of vehicles.","state":"CA","street_address":"425 North Amphlett Blvd.","target_group":null,"transportation_availability":"SAMTRANS stops within 1 block","ttys":null,"urls":["http://www.dmv.ca.gov"],"zipcode":"94401"},{"_id":"51a9fd0128217f8977000050","accessibility_options":["Restroom","Special parking","Wheelchair accessible"],"agency":null,"ask_for":null,"city":"San Mateo","coordinates":[-122.319359,37.562591],"description":"Provides a social model recovery program for alcoholic and drug-abusing individuals, as well as dual diagnosis clients. The Primary program focuses on self-evaluation and awareness (Month 1), planning for the future (Month 2), and putting the plan into action (Month 3). Individual and group counseling looks at all aspects of addiction, recovery, and relapse. Family counseling is also available. Particpants live in shared bedrooms. Women's residential substance abuse treatment is available in a gender-responsive environment, including women only counseling groups. The treatment follows the same phases and provides the same services as the Primary program. Working Man's Program (650-401-8766) is a residential substance abuse recovery program for those with a full-time job. Residents attend individual or group counseling on weekday evenings and weekends. Also, offers clean and sober housing. Residents must abide by curfews and assigned chores, be employed full time, attend AA/NA meetings and a weekly Project Ninety aftercare meeting. Transitional housing is available for up to 18 months. Contact Stacey White, Community Development Manager, at 650-579-7881 for an appointment. Services such as general labor, hauling, moving services, painting, yard work, carpet cleaning, and handy-man services are offered to the community. Contact Stacey White, Community Development Manager, at 650-579-7881 for an appointment. Outpatient Program has been suspended as of October 2011. Additional site located in San Jose. P90 San Jose, 561 South 9th Street, San Jose (408-885-1291).","eligibility_requirements":"Adult males and females with a desire to overcome an addiction to substance(s).","emails":["jstansberry@projectninety.org"],"faxes":["650 579-2640"],"fees":"Vary according to income and ability to pay. Full cost of 90-day residential program is $12,200, or $14,500 for co-occurring treatment services.","funding_sources":null,"how_to_apply":"Apply by attending a Treatment Readiness interview to be assessed for eligibility for treatment. Interview lasts approximately 1.5 hours. No appointment is necessary. Please arrive 15 minutes early. Tuesday at 11am and Friday at 11:45am. 416 2nd Avenue (at Claremont St.), San Mateo, CA 94401. Call 650-579-7881 for more information.","keywords":["ALCOHOLISM SERVICES","Residential Care","DRUG ABUSE SERVICES","Residential Alcoholism Treatment","Residential Drug Abuse Treatment","Women","Men"],"languages_spoken":["Spanish"],"latitude":null,"leaders":null,"longitude":null,"market_match":null,"name":"Project 90.","payments_accepted":null,"phones":[[{"number":"650 579-7881","phone_hours":"(Monday-Friday, 9-5)"}]],"products_sold":null,"service_areas":null,"service_hours":"Monday-Friday, 9-5","service_wait":"1-6 weeks","services_provided":"A residential treatment program for men and women who abuse drugs or alcohol.","state":"CA","street_address":"720 South B Street","target_group":"Adult men and women","transportation_availability":"SAMTRANS stops within 1 block. Carpools can be arranged","ttys":null,"urls":["http://www.projectninety.org"],"zipcode":"94401"},{"_id":"51a9fd0228217f8977000120","accessibility_options":["Elevator","Ramp","Restroom","Wheelchair accessible"],"agency":"San Mateo Adult School.","ask_for":null,"city":"San Mateo","coordinates":[-122.328943,37.576241],"description":"Offers daytime and evening courses in basic education (reading, mathematics and writing), English as a Second Language (ESL), citizenship, vocational training, business and computer skills, arts and crafts, music, languages, social science, parent education, English, science and mathematics. Offers educational and limited vocational counseling to persons who want help in determining what career opportunities are open to them and what education or training they may need. Also offers a General Educational Development (GED) preparation class and is a GED testing center. The adult diploma program for non-concurrently enrolled students utilizes the Adult Learning Center (open entry/exit).","eligibility_requirements":"Age 18 or over","emails":["lteshara@smace.org"],"faxes":["650 762-0232"],"fees":"Vary according to course. English as a Second Language for the semester is a $30 registration fee. Fees vary for vocational and community education classes. Cash, checks and credit cards accepted","funding_sources":null,"how_to_apply":"Walk in or apply by mail. Referral necessary for application to the diploma or GED program if still attending high school. Brochure mailed 3 times annually to all households in the service area","keywords":["EDUCATION SERVICES","Adult","Literacy","English Language","High School Completion/GED","Vocational","EMPLOYMENT/TRAINING SERVICES","Job Counseling/Testing","Community Adult Schools"],"languages_spoken":["Chinese","Spanish"],"latitude":null,"leaders":null,"longitude":null,"market_match":null,"name":"Adult and Community Education.","payments_accepted":null,"phones":[[{"number":"650 558-2100","phone_hours":"(Monday-Thursday, 8 am-9 pm; Friday, 8-4)"}]],"products_sold":null,"service_areas":null,"service_hours":"Monday-Thursday, 8 am-9 pm; Friday, 8-4","service_wait":"Varies according to class","services_provided":"Offers daytime and evening classes in a variety of educational and vocational areas as well as a GED preparation class and testing center.","state":"CA","street_address":"789 East Poplar Avenue","target_group":"Adults","transportation_availability":"SAMTRANS stops within 2 blocks","ttys":null,"urls":["http://www.smace.org"],"zipcode":"94401"},{"_id":"51a9fd0828217f897700055b","accessibility_options":["Elevator","Interpreter for the deaf available","Restroom","Special parking","Wheelchair accessible"],"agency":null,"ask_for":null,"city":"San Mateo","coordinates":[-122.32804,37.565524],"description":"A continuing care retirement community with one- and two-bedroom condominiums available for purchase. Membership and a leasehold condominium interest covers leisure activities, fine dining, housekeeping and laundry service, swimming pool, spa and fitness programs.  An on-site assisted living wing with nurses around the clock and a health and wellness program provides members with security and peace of mind. Monthly fee includes Medicare insurance and long-term care insurance for those who qualify medically.","eligibility_requirements":"Age 60 or over, medically and financially qualified","emails":null,"faxes":["650 579-0446"],"fees":"Prices for condominiums range from $299,000-$800,000. Monthly charge ranges from $2,700-$4,000 (second person add $1,600). Checks and money orders accepted","funding_sources":null,"how_to_apply":"Apply by phone. Medical and financial clearance required","keywords":["HOUSING SERVICES","Senior and Disabled Housing","Older Adult/Disability Related Supportive Housing","Older Adults"],"languages_spoken":["Chinese (Cantonese)","Chinese (Mandarin)","Filipino (Tagalog)","French","German","Italian","Spanish","Swedish"],"latitude":null,"leaders":null,"longitude":null,"market_match":null,"name":"Peninsula Regent.","payments_accepted":null,"phones":[[{"number":"650 579-5500","phone_hours":"(24 hours daily)"}]],"products_sold":null,"service_areas":null,"service_hours":"24-hour facility","service_wait":"Varies according to availability of units","services_provided":"A life care retirement complex.","state":"CA","street_address":"1 Baldwin Avenue","target_group":"Seniors age 60 or over","transportation_availability":"SAMTRANS stops within 1 block","ttys":null,"urls":["http://peninsularegent.com"],"zipcode":"94401"},{"_id":"51a9fd0228217f89770000f2","accessibility_options":["Elevator"],"agency":null,"ask_for":null,"city":"San Mateo","coordinates":[-122.320629,37.561859],"description":"Low- to moderate-cost housing for senior citizens age 62 or over, capable of self care, who meet the income eligibility requirement. A security deposit equal to one month's rent required at time of signing the lease. Each resident must sign up for meals. There are 200 units in a 12-story high rise. Units are unfurnished except for mini-blinds and carpets. There is a social hall, laundry, library, music room, billiards room and dining room. A social service coordinator and public health nurse are also on staff. Formerly known as Park Towers.","eligibility_requirements":"Age 62 or over and capable of independent living. Maximum income: $63,350 per year for a single, $72,400 per year for a couple","emails":["mgervasi@lesleysc.org"],"faxes":["650 342-4156"],"fees":"Studio $344-$470 per month, 1 bedroom $635-$678 per month. Mandatory meal program $265 per month. Checks and money orders accepted","funding_sources":null,"how_to_apply":"Call for appointment","keywords":["HOUSING SERVICES","Senior and Disabled Housing","Older Adult/Disability Related Supportive Housing","Older Adults"],"languages_spoken":["Chinese (Cantonese)","Chinese (Mandarin)","Spanish"],"latitude":null,"leaders":null,"longitude":null,"market_match":null,"name":"Lesley Towers.","payments_accepted":null,"phones":[[{"number":"650 342-2051","phone_hours":"(Monday-Friday, 8-4:30)"}]],"products_sold":null,"service_areas":null,"service_hours":"Monday-Friday, 8-4:30","service_wait":"Approximately 1 month for studio, 1 year for 1 bedroom (double occupancy), 2 years for 1 bedroom (single occupancy)","services_provided":"Low- to moderate-cost housing for ambulatory senior citizens.","state":"CA","street_address":"700 Laurel Avenue","target_group":"Senior citizens","transportation_availability":"SAMTRANS stops within 2 blocks","ttys":null,"urls":["http://www.lesleyfoundation.org"],"zipcode":"94401"},{"_id":"51a9fd0428217f8977000242","accessibility_options":["Wheelchair accessible"],"agency":null,"ask_for":null,"city":"San Mateo","coordinates":[-122.320118,37.560403],"description":"A nonprofit volunteer organization whose purpose is to benefit the community by establishing an oasis in Central Park, collecting, cultivating and displaying unique and diverse plant species, and promoting a knowledge and interest in gardening throughout the community. An annual garden tour is held in fall. The board of directors meets the third Wednesday of each month. New officers elected yearly. Educational programs are presented at the Kohl Pump House in Central Park throughout the year.  The greenhouses are open for sale of plants Tuesdays and Thursdays, 10 am-3 pm, and Sundays, 10-noon.","eligibility_requirements":"None","emails":null,"faxes":null,"fees":"Dues begin at $25 annually ($30 for senior couple). Checks accepted","funding_sources":null,"how_to_apply":null,"keywords":["Horticultural Societies"],"languages_spoken":null,"latitude":null,"leaders":null,"longitude":null,"market_match":null,"name":"San Mateo Arboretum Society.","payments_accepted":null,"phones":[[{"number":"650 579-0536","department":"(24-hour answering machine)"}]],"products_sold":null,"service_areas":null,"service_hours":"Tuesday, Thursday, 10-3; Sunday, 10-noon","service_wait":null,"services_provided":null,"state":"CA","street_address":"101 9th Avenue","target_group":"Gardeners, people interested in houseplants or yard plants","transportation_availability":"SAMTRANS stops within 2 blocks","ttys":null,"urls":["http://www.sanmateoarboretum.org"],"zipcode":"94401"},{"_id":"51a9fd0328217f89770001c3","accessibility_options":["Not wheelchair accessible at this time"],"agency":null,"ask_for":null,"city":"San Mateo","coordinates":[-122.334326,37.573874],"description":"Operation School Bell is a volunteer service that provides two complete sets of new clothes for a child in the San Mateo-Foster City, Redwood City or Millbrae school districts or San Bruno Belle Aire School. After checking with parent, all referrals should be made to the school principal, nurse or school social worker who then refers to Operation School Bell. This service is available only during the school year and children are transported from the school to the clothing outlet. The Turnstyle Shop, 60 North B Street, San Mateo, is a resale shop for used clothing, small appliances and household items. Receipts from the shop support community service efforts of the Assistance League and Peninsula Auxiliary for Children. Friendly Visiting Service is no longer in operation as of 2008.","eligibility_requirements":"Child in need who attends public school in San Mateo County","emails":null,"faxes":null,"fees":"None","funding_sources":null,"how_to_apply":"Appointment made through school principal","keywords":["COMMODITY SERVICES","Clothing/Personal Items","School Clothing","Youth"],"languages_spoken":null,"latitude":null,"leaders":null,"longitude":null,"market_match":null,"name":"Assistance League of San Mateo County.","payments_accepted":null,"phones":[[{"number":"650 344-7896","department":"Operation School Bell","phone_hours":"(Friday, 9 am-12 pm)"}],[{"number":"650 342-2367","department":"Turnstyle Shop"}]],"products_sold":null,"service_areas":null,"service_hours":null,"service_wait":"Scheduled by school","services_provided":"Supplies clothes to needy children in the San Mateo-Foster City, Millbrae and Redwood City school districts.","state":"CA","street_address":"528 North San Mateo Drive","target_group":"Children","transportation_availability":"Transportation provided by school","ttys":null,"urls":["http://sanmateocounty.assistanceleague.org"],"zipcode":"94401"},{"_id":"51a9fd0228217f89770000af","accessibility_options":["Ramp","Special parking"],"agency":"Superior Court of California, County of San Mateo.","ask_for":null,"city":"San Mateo","coordinates":[-122.328997,37.581418],"description":"Traffic Court hears cases for tickets issued in Belmont, Burlingame, Foster City, Half Moon Bay, Hillsborough, Millbrae, San Mateo or at San Francisco International Airport. Small Claims Court hears cases where there has been personal injury or damage to property, or broken contracts or obligations and the amount of money involved does not exceed $5,000 (limit for businesses) or $7,500 (limit for individuals). This court handles claims when the defendant resides in the judicial district served or the claim is on an action that took place within the district. Plaintiffs must be age 18 or over and the claim must be filed by the original owner of the claim. Hearings are scheduled approximately 30-40 days after the filing date when the defendant is a county resident and up to 70 days for nonresidents. Lawyers are not allowed to represent people in small claims courts. Non-English speaking people must provide their own interpreter. Small Claims Advisory workshops provide assistance for litigants in these cases. The workshops are offered the first Wednesday, 5-7 pm (not including the first week of the month), and Thursday, 2:30-4:30pm in Conference Room H.","eligibility_requirements":"None","emails":null,"faxes":null,"fees":"Small claims filing fees. Cash, checks, credit cards and money orders accepted","funding_sources":null,"how_to_apply":"Walk in or apply by phone or mail","keywords":["LEGAL AND CRIMINAL JUSTICE SERVICES","Courts","Mediation","Civil State Trial Courts","Traffic Courts"],"languages_spoken":["Spanish"],"latitude":null,"leaders":null,"longitude":null,"market_match":null,"name":"Central Branch.","payments_accepted":null,"phones":[[{"number":"650 573-2622","department":"Traffic","phone_hours":"(Monday-Thursday, 7:30-4; Friday, 8-4)"}],[{"number":"650 363-4303"}]],"products_sold":null,"service_areas":null,"service_hours":"Monday-Thursday, 7:30-4; Friday, 8-4","service_wait":"Varies","services_provided":"Handles traffic cases for the mid-county area.","state":"CA","street_address":"800 North Humboldt Street","target_group":null,"transportation_availability":"SAMTRANS stops within 1 block","ttys":null,"urls":["http://www.sanmateocourt.org"],"zipcode":"94401"},{"_id":"51a9fd0128217f8977000062","accessibility_options":["Pathways (some)","Playground","Restroom","Special parking","Wheelchair accessible"],"agency":"San Mateo County Parks Department.","ask_for":null,"city":"San Mateo","coordinates":[-122.326357,37.586346],"description":"Open all year, dawn to dusk, the 727-acre park offers the following facilities: picnic sites, group picnic areas, marina, bay swimming, fishing, playground, environmental science museum, rifle and pistol range, boat launching ramp, kayaking, windsurfing, shorebird viewing, saltwater marsh area, sand volleyball areas, and animal center. The playground is wheelchair accessible. Group picnics require reservations for groups of 50 or more. No overnight camping. Stores nearby. No pets allowed. No fee for senior citizens except on weekends and holidays.","eligibility_requirements":"None","emails":["parksandrecreation@co.sanmateo.ca.us"],"faxes":["650 573-3727"],"fees":"$5 per car. Open group areas rent for a minimum of $50. Rate varies depending on size area. Cash / Vehicle entry; Credit card / Reservations","funding_sources":null,"how_to_apply":"Phone Reservations for group permit or go to Web site","keywords":["RECREATION/LEISURE SERVICES","Parks/Playground","City/County Parks"],"languages_spoken":null,"latitude":null,"leaders":null,"longitude":null,"market_match":null,"name":"Coyote Point Recreation Area.","payments_accepted":null,"phones":[[{"number":"650 573-2592","department":"Information"}],[{"number":"650 363-4021","department":"Reservations","phone_hours":"(Monday-Thursday, 8-6)"}]],"products_sold":null,"service_areas":null,"service_hours":"Daily, 8 am-dusk","service_wait":"Varies according to season","services_provided":"A 727-acre park on San Francisco Bay with picnic sites, playground, marina, bay swimming and fishing, rifle and pistol range.","state":"CA","street_address":"1701 Coyote Point Drive","target_group":null,"transportation_availability":"SAMTRANS stops within 1 mile","ttys":["650 325-6973"],"urls":["http://www.eparks.net"],"zipcode":"94401"},{"_id":"51a9fd0228217f897700014f","accessibility_options":["Wheelchair accessible"],"agency":"YMCA of San Francisco.","ask_for":null,"city":"San Mateo","coordinates":[-122.305187,37.55958],"description":"Offers counseling services, outreach programs, health and wellbeing classes, youth wellness center, Living Strong, Living Well (a program for recovering cancer patients) and Building Futures Mentoring program. Three counseling centers include the the Pacifica Youth Services Bureau, the San Mateo Youth Service Bureau, and the South San Francisco Youth Service Bureau. Also offers over 100 fitness classes a week including cycle, bosu sport, kick boxing, boot camp and Pilates. Offers a variety of programs for youth and older adults including seasonal day camps, swim lessons, aqua aerobics, sports programs and outdoor excursions. Complimentary babysitting is included in all family memberships.","eligibility_requirements":"None","emails":["rfischer@ymcasf.org"],"faxes":["650 286-0128"],"fees":"Annual memberships. Fees for some classes and services. Cash, checks, credit cards and electronic transfers accepted","funding_sources":null,"how_to_apply":"Walk in or apply by phone, mail or email","keywords":["INDIVIDUAL AND FAMILY DEVELOPMENT SERVICES","Companion","Parent Groups","RECREATION/LEISURE SERVICES","Camping","Field Trips/Travel","Parks/Playground","Sports/Games/Exercise","Y Facilities","Youth"],"languages_spoken":["Spanish"],"latitude":null,"leaders":null,"longitude":null,"market_match":null,"name":"Peninsula Family YMCA.","payments_accepted":null,"phones":[[{"number":"650 286-9622","phone_hours":"(Monday-Friday, 5:30 am-10 pm; Saturday, 7-7; Sunday, 8-7)"}]],"products_sold":null,"service_areas":null,"service_hours":"Monday-Friday, 5:30 am-10 pm; Saturday, 7 am-7 pm; Sunday, 8-7","service_wait":"No wait","services_provided":"Provides social, physical education and recreational activities for all ages.","state":"CA","street_address":"1877 South Grant Street","target_group":"Youth, teens, adults, seniors, families","transportation_availability":"SAMTRANS stops within 1 block","ttys":null,"urls":["http://www.ymcasf.org/peninsula"],"zipcode":"94402"},{"_id":"51a9fd0928217f8977000653","accessibility_options":null,"agency":null,"ask_for":null,"city":"San Mateo","coordinates":[-122.321498,37.553378],"description":"Encourages bicycling and walking as a means of transportation and recreation, educates people about proper cycling techniques and lobbies government to accommodate and promote bicycle and pedestrian facilities and accommodation. All are invited to join. Meetings are held the first Thursday of the month, 6:30 pm, at Ladda's Thai Cuisine, 2053 Broadway Street, Redwood City (3 blocks from the Redwood City Caltrain Station). Call, write or e-mail for a free copy of the newsletter, \"The Spinning Crank.\"","eligibility_requirements":"None","emails":["info@penbiped.net"],"faxes":null,"fees":"$35 per year","funding_sources":null,"how_to_apply":null,"keywords":["Planning/Coordinating/Advisory Groups","Transportation Issues"],"languages_spoken":null,"latitude":null,"leaders":null,"longitude":null,"market_match":null,"name":"Peninsula Bicycle and Pedestrian Coalition.","payments_accepted":null,"phones":[[{"number":"650 571-5830","phone_hours":"(24 hours daily)"}]],"products_sold":null,"service_areas":null,"service_hours":null,"service_wait":null,"services_provided":"Encourages bicycling and walking as a means of transportation.","state":"CA","street_address":"1214 Nadina Street","target_group":"Bicyclists, traffic engineers, pedestrian advocates","transportation_availability":null,"ttys":null,"urls":["http://www.penbiped.net"],"zipcode":"94402"},{"_id":"51a9fd0228217f897700014e","accessibility_options":["Elevator","Ramp","Wheelchair accessible"],"agency":null,"ask_for":null,"city":"Burlingame","coordinates":[-122.342817,37.580411],"description":"A 67-unit assisted-living residence for adults capable of self care. Will accept persons with canes or walkers. Studio and one-bedroom apartments are available. Services include: 3 meals prepared daily; housekeeping and laundry; fully-supervised activities program; utilities, including cable TV (except telephone); and transportation scheduling. Features include: private dining room for guests; individual air conditioning and heating; beauty salon and barber shop; patios/balconies; pool table; 24-hour snack and beverage availability; garage parking; 24-hour staff; and pendant emergency response system. Assisted-living services include: medication; assistance with bathing, showers, dressing and personal hygiene; escort to meals and activities; extra assistance with housekeeping; and evening assistance at bedtime.   Formerly known as Retiremnt Inn of Burlingame.","eligibility_requirements":"Must be physically and mentally able to function without medical supervision. Cane or walker acceptable","emails":["charmaine.doherty@atriaseniorliving.com"],"faxes":["650 343-0225"],"fees":"Fees start at $2,675 per month single occupancy in independent living. Assisted living fees start at $255 per month. Checks accepted","funding_sources":null,"how_to_apply":"Walk in or apply by phone for a tour","keywords":["HOUSING SERVICES","Senior and Disabled Housing","Older Adult/Disability Related Supportive Housing","Older Adults"],"languages_spoken":["Chinese (Mandarin)","Filipino (Tagalog)","Spanish"],"latitude":null,"leaders":null,"longitude":null,"market_match":null,"name":"Atria Burlingame.","payments_accepted":null,"phones":[[{"number":"650 343-2747","department":"(Daily, 8-7)"}]],"products_sold":null,"service_areas":null,"service_hours":"24 hours daily","service_wait":"No wait","services_provided":"An assisted living residence for adults capable of self care.","state":"CA","street_address":"250 Myrtle Road","target_group":"Senior citizens, independent and assisted","transportation_availability":"CALTRAIN stops within 2 blocks. Scheduled van service","ttys":null,"urls":["http://www.atriaburlingame.com"],"zipcode":"94010"},{"_id":"51a9fd0928217f897700066a","accessibility_options":["Wheelchair accessible"],"agency":null,"ask_for":null,"city":"Burlingame","coordinates":[-122.343824,37.579036],"description":"A museum dedicated to the candy and the plastic dispensers which originally appeared in the 1950s. The collection numbers more than 500 dispensers as well as examples of advertising, vending machines and unusual Pez accessories.","eligibility_requirements":"None","emails":["pez@spectrumnet.com"],"faxes":null,"fees":"Adults, $3; children ages 4-12, $1","funding_sources":null,"how_to_apply":null,"keywords":["Museums"],"languages_spoken":null,"latitude":null,"leaders":null,"longitude":null,"market_match":null,"name":"Burlingame Museum of Pez Memorabilia.","payments_accepted":null,"phones":[[{"number":"650 347-2301"}]],"products_sold":null,"service_areas":null,"service_hours":null,"service_wait":null,"services_provided":null,"state":"CA","street_address":"214 California Drive","target_group":null,"transportation_availability":null,"ttys":null,"urls":["http://www.burlingamepezmuseum.com"],"zipcode":"94010"},{"_id":"51a9fd0728217f89770004cf","accessibility_options":["Wheelchair accessible"],"agency":null,"ask_for":null,"city":"Burlingame","coordinates":[-122.342995,37.581519],"description":"A social club with membership open to all citizens of the area served, age 55 or over. Activities include hot luncheons, bazaars, fundraisers and bingo. Meets every Friday, 11 am-3 pm, at the Burlingame Recreation Center, 850 Burlingame Avenue, Burlingame.","eligibility_requirements":"Age 55 or over","emails":null,"faxes":null,"fees":"$12 annual dues. Cash and checks accepted","funding_sources":null,"how_to_apply":"Membership","keywords":["Older Adults"],"languages_spoken":["Italian","Spanish"],"latitude":null,"leaders":null,"longitude":null,"market_match":null,"name":"Senior Citizen Organization of Burlingame, Inc..","payments_accepted":null,"phones":[[{"number":"650 347-0868","phone_hours":"(Friday, 11-3)"}]],"products_sold":null,"service_areas":null,"service_hours":"Friday, 11-3","service_wait":"No wait","services_provided":"A social club for persons age 65 or over.","state":"CA","street_address":"850 Burlingame Avenue","target_group":"Seniors","transportation_availability":null,"ttys":null,"urls":null,"zipcode":"94010"},{"_id":"51a9fd0428217f8977000271","accessibility_options":["Restroom","Special parking","Wheelchair accessible"],"agency":null,"ask_for":null,"city":"Burlingame","coordinates":[-122.342995,37.581519],"description":"Provides free coffee and dessert on Tuesdays, 12-3 pm. Seniors bring a bag lunch and play bingo.","eligibility_requirements":"Age 60 or over and spouse of any age","emails":null,"faxes":["650 696-7216"],"fees":"None. Cash accepted","funding_sources":null,"how_to_apply":"Walk in or apply by phone ","keywords":["ADULT PROTECTION AND CARE SERVICES","Meal Sites/Home-delivered Mea","Senior Centers","Older Adults"],"languages_spoken":null,"latitude":null,"leaders":null,"longitude":null,"market_match":null,"name":"Burlingame Senior Nutrition Program.","payments_accepted":null,"phones":[[{"number":"650 558-7300","phone_hours":"(Monday-Friday, 8-5)"}]],"products_sold":null,"service_areas":null,"service_hours":null,"service_wait":"No wait","services_provided":null,"state":"CA","street_address":"850 Burlingame Avenue","target_group":"Senior citizens, age 60 or over","transportation_availability":"SAMTRANS stops within 3 blocks","ttys":null,"urls":["http://www.burlingame.org"],"zipcode":"94010"},{"_id":"51a9fd0328217f8977000216","accessibility_options":["Wheelchair accessible"],"agency":null,"ask_for":null,"city":"Burlingame","coordinates":[-122.345867,37.575713],"description":"A telephone and drop-in information and referral service for low-income residents of the mid-county area who need information and/or referral to social or community services or help with a problem. The goal is to work with each individual to understand the concerns and assist each toward self sufficiency.   Funds designated for emergency assistance are used to provide groceries and other services.","eligibility_requirements":"Low-income resident of area served","emails":["contact@callprimrose.org"],"faxes":null,"fees":"None","funding_sources":null,"how_to_apply":"Walk in","keywords":["Emergency Food","Housing Expense Assistance","Utility Assistance","Mobility Aids","Information and Referral","Low Income"],"languages_spoken":null,"latitude":null,"leaders":null,"longitude":null,"market_match":null,"name":"CALL - Primrose Center.","payments_accepted":null,"phones":[[{"number":"650 342-2255","phone_hours":"(Monday-Friday, 9-3)"}],[{"department":"650-342-CALL"}]],"products_sold":null,"service_areas":null,"service_hours":"Monday-Friday, 9-3","service_wait":"Usually no wait","services_provided":"An information and referral and emergency assistance service for all residents of the mid-county area.","state":"CA","street_address":"139 Primrose Road","target_group":"Mid-county residents needing social or community services","transportation_availability":"SAMTRANS stops within 2 blocks","ttys":null,"urls":["http://www.callprimrose.org"],"zipcode":"94010"}],"count":30,"pagination":{"previous":null,"next":2,"current":1,"per_page":30,"count":48,"pages":2}}